redis_search_django/__init__.py
redis_search_django/apps.py
redis_search_django/config.py
redis_search_django/documents.py
redis_search_django/mixins.py
redis_search_django/paginator.py
redis_search_django/py.typed
redis_search_django/query.py
redis_search_django/registry.py
redis_search_django/signals.py
redis_search_django/management/__init__.py
redis_search_django/management/commands/__init__.py
redis_search_django/management/commands/index.py
redis_search_django-0.1.0.dist-info/LICENSE
redis_search_django-0.1.0.dist-info/METADATA
redis_search_django-0.1.0.dist-info/WHEEL
redis_search_django-0.1.0.dist-info/top_level.txt
redis_search_django-0.1.0.dist-info/RECORD
