Metadata-Version: 2.1
Name: redis-search-django
Version: 0.1.0
Summary: Django Integration with Redis Search
Home-page: https://github.com/saadmk11/redis-search-django
Author: Maksudul Haque
Author-email: saad.mk112@gmail.com
License: MIT
Keywords: Django,Redis,Search,RediSearch
Classifier: Development Status :: 4 - Beta
Classifier: Natural Language :: English
Classifier: Intended Audience :: Developers
Classifier: License :: OSI Approved :: MIT License
Classifier: Operating System :: OS Independent
Classifier: Framework :: Django :: 3.2
Classifier: Framework :: Django :: 4.0
Classifier: Framework :: Django :: 4.1
Classifier: Programming Language :: Python :: 3 :: Only
Classifier: Programming Language :: Python :: 3
Classifier: Programming Language :: Python :: 3.7
Classifier: Programming Language :: Python :: 3.8
Classifier: Programming Language :: Python :: 3.9
Classifier: Programming Language :: Python :: 3.10
Requires-Python: >=3.7
License-File: LICENSE
Requires-Dist: django (>=3.2)
Requires-Dist: redis-om (>=0.0.27)
